{"nodes": [{"group": "809.0", "name": "10.1103/PhysRevLett.100.258106"}, {"group": "809.0", "name": "10.1103/PhysRevLett.102.058103"}, {"group": "809.0", "name": "10.1103/PhysRevLett.102.174501"}, {"group": "809.0", "name": "10.1103/PhysRevLett.102.198103"}, {"group": "809.0", "name": "10.1103/PhysRevLett.103.048101"}, {"group": "809.0", "name": "10.1103/PhysRevLett.103.158102"}, {"group": "809.0", "name": "10.1103/PhysRevLett.104.218101"}, {"group": "809.0", "name": "10.1103/PhysRevLett.105.108104"}, {"group": "809.0", "name": "10.1103/PhysRevLett.105.248103"}, {"group": "809.0", "name": "10.1103/PhysRevLett.107.128101"}, {"group": "809.0", "name": "10.1103/PhysRevLett.107.188102"}, {"group": "809.0", "name": "10.1103/PhysRevLett.107.258103"}, {"group": "809.0", "name": "10.1103/PhysRevLett.108.074502"}, {"group": "809.0", "name": "10.1103/PhysRevLett.108.188101"}, {"group": "809.0", "name": "10.1103/PhysRevLett.108.198101"}, {"group": "809.0", "name": "10.1103/PhysRevLett.108.238107"}, {"group": "809.0", "name": "10.1103/PhysRevLett.108.258103"}, {"group": "809.0", "name": "10.1103/PhysRevLett.108.258104"}, {"group": "809.0", "name": "10.1103/PhysRevLett.109.108101"}, {"group": "809.0", "name": "10.1103/PhysRevLett.109.144502"}, {"group": "809.0", "name": "10.1103/PhysRevLett.111.034502"}, {"group": "809.0", "name": "10.1103/PhysRevLett.111.108102"}, {"group": "809.0", "name": "10.1103/PhysRevLett.98.018102"}, {"group": "809.0", "name": "10.1103/PhysRevLett.98.168103"}, {"group": "809.0", "name": "10.1103/PhysRevLett.99.214102"}, {"group": "809.0", "name": "10.1103/PhysRevLett.99.228104"}, {"group": "809.0", "name": "10.1103/RevModPhys.85.1327"}], "links": [{"source": 8, "target": 4, "value": 1}, {"source": 26, "target": 7, "value": 1}, {"source": 14, "target": 8, "value": 1}, {"source": 19, "target": 2, "value": 1}, {"source": 20, "target": 2, "value": 1}, {"source": 21, "target": 11, "value": 1}, {"source": 14, "target": 4, "value": 1}, {"source": 12, "target": 2, "value": 1}, {"source": 11, "target": 0, "value": 1}, {"source": 11, "target": 3, "value": 1}, {"source": 19, "target": 0, "value": 1}, {"source": 16, "target": 17, "value": 1}, {"source": 18, "target": 9, "value": 1}, {"source": 14, "target": 6, "value": 1}, {"source": 17, "target": 16, "value": 1}, {"source": 3, "target": 24, "value": 1}, {"source": 19, "target": 12, "value": 1}, {"source": 26, "target": 4, "value": 1}, {"source": 26, "target": 9, "value": 1}, {"source": 18, "target": 14, "value": 1}, {"source": 11, "target": 25, "value": 1}, {"source": 11, "target": 23, "value": 1}, {"source": 26, "target": 18, "value": 1}, {"source": 21, "target": 0, "value": 1}, {"source": 13, "target": 5, "value": 1}, {"source": 26, "target": 15, "value": 1}, {"source": 20, "target": 19, "value": 1}, {"source": 21, "target": 18, "value": 1}, {"source": 26, "target": 8, "value": 1}, {"source": 26, "target": 14, "value": 1}, {"source": 26, "target": 5, "value": 1}, {"source": 16, "target": 25, "value": 1}, {"source": 26, "target": 13, "value": 1}, {"source": 14, "target": 9, "value": 1}, {"source": 11, "target": 7, "value": 1}, {"source": 1, "target": 0, "value": 1}, {"source": 20, "target": 12, "value": 1}, {"source": 21, "target": 7, "value": 1}]}