{"nodes": [{"group": "1220.0", "name": "10.1103/PhysRevLett.100.028301"}, {"group": "1220.0", "name": "10.1103/PhysRevLett.100.050602"}, {"group": "1220.0", "name": "10.1103/PhysRevLett.100.108302"}, {"group": "1220.0", "name": "10.1103/PhysRevLett.100.186104"}, {"group": "1220.0", "name": "10.1103/PhysRevLett.101.045701"}, {"group": "1220.0", "name": "10.1103/PhysRevLett.101.058302"}, {"group": "1220.0", "name": "10.1103/PhysRevLett.102.015504"}, {"group": "1220.0", "name": "10.1103/PhysRevLett.102.048301"}, {"group": "1220.0", "name": "10.1103/PhysRevLett.103.035702"}, {"group": "1220.0", "name": "10.1103/PhysRevLett.103.045703"}, {"group": "1220.0", "name": "10.1103/PhysRevLett.103.118302"}, {"group": "1220.0", "name": "10.1103/PhysRevLett.103.118303"}, {"group": "1220.0", "name": "10.1103/PhysRevLett.103.188302"}, {"group": "1220.0", "name": "10.1103/PhysRevLett.105.045702"}, {"group": "1220.0", "name": "10.1103/PhysRevLett.105.068001"}, {"group": "1220.0", "name": "10.1103/PhysRevLett.105.078301"}, {"group": "1220.0", "name": "10.1103/PhysRevLett.105.137203"}, {"group": "1220.0", "name": "10.1103/PhysRevLett.105.245701"}, {"group": "1220.0", "name": "10.1103/PhysRevLett.106.095504"}, {"group": "1220.0", "name": "10.1103/PhysRevLett.106.115704"}, {"group": "1220.0", "name": "10.1103/PhysRevLett.106.195502"}, {"group": "1220.0", "name": "10.1103/PhysRevLett.106.215501"}, {"group": "1220.0", "name": "10.1103/PhysRevLett.106.255501"}, {"group": "1220.0", "name": "10.1103/PhysRevLett.107.045902"}, {"group": "1220.0", "name": "10.1103/PhysRevLett.107.085503"}, {"group": "1220.0", "name": "10.1103/PhysRevLett.107.135701"}, {"group": "1220.0", "name": "10.1103/PhysRevLett.107.155501"}, {"group": "1220.0", "name": "10.1103/PhysRevLett.107.215702"}, {"group": "1220.0", "name": "10.1103/PhysRevLett.108.074504"}, {"group": "1220.0", "name": "10.1103/PhysRevLett.108.165502"}, {"group": "1220.0", "name": "10.1103/PhysRevLett.108.226101"}, {"group": "1220.0", "name": "10.1103/PhysRevLett.108.226102"}, {"group": "1220.0", "name": "10.1103/PhysRevLett.109.016101"}, {"group": "1220.0", "name": "10.1103/PhysRevLett.109.225502"}, {"group": "1220.0", "name": "10.1103/PhysRevLett.109.228301"}, {"group": "1220.0", "name": "10.1103/PhysRevLett.110.148303"}, {"group": "1220.0", "name": "10.1103/PhysRevLett.110.255503"}, {"group": "1220.0", "name": "10.1103/PhysRevLett.111.015501"}, {"group": "1220.0", "name": "10.1103/PhysRevLett.111.165501"}, {"group": "1220.0", "name": "10.1103/PhysRevLett.112.255501"}, {"group": "1220.0", "name": "10.1103/PhysRevLett.98.035703"}, {"group": "1220.0", "name": "10.1103/PhysRevLett.98.135501"}, {"group": "1220.0", "name": "10.1103/PhysRevLett.98.188304"}, {"group": "1220.0", "name": "10.1103/PhysRevLett.98.195502"}, {"group": "1220.0", "name": "10.1103/PhysRevLett.98.225505"}, {"group": "1220.0", "name": "10.1103/PhysRevLett.98.235502"}, {"group": "1220.0", "name": "10.1103/PhysRevLett.99.055501"}, {"group": "1220.0", "name": "10.1103/PhysRevLett.99.107801"}, {"group": "1220.0", "name": "10.1103/PhysRevLett.99.118302"}, {"group": "1220.0", "name": "10.1103/PhysRevLett.99.235503"}, {"group": "1220.0", "name": "10.1103/PhysRevLett.99.235702"}, {"group": "1220.0", "name": "10.1103/PhysRevLett.99.248301"}, {"group": "1220.0", "name": "10.1103/PhysRevLett.99.268301"}, {"group": "1220.0", "name": "10.1103/RevModPhys.85.921"}], "links": [{"source": 27, "target": 5, "value": 1}, {"source": 30, "target": 2, "value": 1}, {"source": 36, "target": 27, "value": 1}, {"source": 24, "target": 16, "value": 1}, {"source": 17, "target": 0, "value": 1}, {"source": 15, "target": 5, "value": 1}, {"source": 38, "target": 47, "value": 1}, {"source": 13, "target": 8, "value": 1}, {"source": 9, "target": 1, "value": 1}, {"source": 38, "target": 44, "value": 1}, {"source": 20, "target": 8, "value": 1}, {"source": 35, "target": 11, "value": 1}, {"source": 29, "target": 24, "value": 1}, {"source": 23, "target": 4, "value": 1}, {"source": 23, "target": 6, "value": 1}, {"source": 23, "target": 50, "value": 1}, {"source": 53, "target": 32, "value": 1}, {"source": 34, "target": 0, "value": 1}, {"source": 26, "target": 12, "value": 1}, {"source": 34, "target": 50, "value": 1}, {"source": 29, "target": 44, "value": 1}, {"source": 8, "target": 2, "value": 1}, {"source": 30, "target": 8, "value": 1}, {"source": 35, "target": 7, "value": 1}, {"source": 37, "target": 26, "value": 1}, {"source": 34, "target": 47, "value": 1}, {"source": 14, "target": 9, "value": 1}, {"source": 33, "target": 44, "value": 1}, {"source": 21, "target": 6, "value": 1}, {"source": 0, "target": 47, "value": 1}, {"source": 53, "target": 3, "value": 1}, {"source": 29, "target": 16, "value": 1}, {"source": 17, "target": 50, "value": 1}, {"source": 36, "target": 18, "value": 1}, {"source": 37, "target": 12, "value": 1}, {"source": 38, "target": 28, "value": 1}, {"source": 39, "target": 43, "value": 1}, {"source": 36, "target": 49, "value": 1}, {"source": 36, "target": 33, "value": 1}, {"source": 18, "target": 44, "value": 1}, {"source": 38, "target": 34, "value": 1}, {"source": 39, "target": 44, "value": 1}, {"source": 39, "target": 49, "value": 1}, {"source": 0, "target": 50, "value": 1}, {"source": 20, "target": 2, "value": 1}, {"source": 38, "target": 49, "value": 1}, {"source": 50, "target": 47, "value": 1}, {"source": 27, "target": 49, "value": 1}, {"source": 34, "target": 17, "value": 1}, {"source": 53, "target": 13, "value": 1}, {"source": 37, "target": 25, "value": 1}, {"source": 27, "target": 9, "value": 1}, {"source": 53, "target": 31, "value": 1}, {"source": 23, "target": 7, "value": 1}, {"source": 36, "target": 44, "value": 1}, {"source": 39, "target": 33, "value": 1}, {"source": 17, "target": 51, "value": 1}, {"source": 39, "target": 38, "value": 1}, {"source": 14, "target": 11, "value": 1}, {"source": 27, "target": 15, "value": 1}, {"source": 25, "target": 6, "value": 1}, {"source": 33, "target": 18, "value": 1}, {"source": 35, "target": 14, "value": 1}]}