{"nodes": [{"index": 0, "group": "8", "name": "493", "size": 227}, {"index": 1, "group": "26", "name": "1000", "size": 216}, {"index": 2, "group": "3", "name": "253", "size": 200}, {"index": 3, "group": "29", "name": "1195", "size": 98}, {"index": 4, "group": "22", "name": "940", "size": 64}, {"index": 5, "group": "10", "name": "598", "size": 64}, {"index": 6, "group": "21", "name": "882", "size": 61}, {"index": 7, "group": "20", "name": "875", "size": 55}], "links": [{"source": 3, "target": 7, "value": 3.0}, {"source": 4, "target": 1, "value": 31.0}, {"source": 2, "target": 6, "value": 1.0}, {"source": 7, "target": 3, "value": 7.0}, {"source": 7, "target": 0, "value": 5.0}, {"source": 5, "target": 2, "value": 1.0}, {"source": 5, "target": 0, "value": 6.0}, {"source": 3, "target": 0, "value": 3.0}, {"source": 4, "target": 0, "value": 2.0}, {"source": 1, "target": 2, "value": 4.0}, {"source": 0, "target": 5, "value": 6.0}, {"source": 6, "target": 0, "value": 3.0}, {"source": 0, "target": 7, "value": 3.0}, {"source": 1, "target": 0, "value": 4.0}, {"source": 0, "target": 3, "value": 9.0}, {"source": 3, "target": 2, "value": 1.0}, {"source": 4, "target": 6, "value": 2.0}, {"source": 1, "target": 6, "value": 5.0}, {"source": 6, "target": 1, "value": 5.0}, {"source": 1, "target": 4, "value": 10.0}, {"source": 0, "target": 6, "value": 3.0}, {"source": 2, "target": 1, "value": 3.0}, {"source": 0, "target": 1, "value": 3.0}, {"source": 0, "target": 2, "value": 2.0}, {"source": 6, "target": 4, "value": 1.0}, {"source": 3, "target": 5, "value": 2.0}, {"source": 6, "target": 2, "value": 4.0}, {"source": 2, "target": 0, "value": 4.0}, {"source": 5, "target": 7, "value": 1.0}, {"source": 2, "target": 3, "value": 5.0}, {"source": 5, "target": 3, "value": 5.0}]}